opsdata_coal_node/__init__.py
opsdata_coal_node/core.py
opsdata_coal_node/version.py
opsdata_coal_node/coal_node/events/.index.db
opsdata_coal_node/coal_node/events/2019/01/19/2019-01-19T10-02-16-1584c.xml
opsdata_coal_node/coal_node/events/2019/01/19/2019-01-19T13-57-15-4e5aa.xml
opsdata_coal_node/coal_node/events/2019/01/21/2019-01-21T11-50-32-914c4.xml
opsdata_coal_node/coal_node/events/2019/01/24/2019-01-24T01-58-00-026af.xml
opsdata_coal_node/coal_node/events/2019/01/28/2019-01-28T20-54-47-e20c3.xml
opsdata_coal_node/coal_node/stations/inv.xml
opsdata_coal_node/coal_node/waveforms/.index.h5
opsdata_coal_node/coal_node/waveforms/2018-05-22T17-02-16.mseed
opsdata_coal_node/coal_node/waveforms/2018-05-22T20-57-15.mseed
opsdata_coal_node/coal_node/waveforms/2018-05-24T18-50-32.mseed
opsdata_coal_node/coal_node/waveforms/2018-05-27T08-58-00.mseed
opsdata_coal_node/coal_node/waveforms/2018-06-01T03-54-47.mseed
opsdata_coal_node-0.1.5.data/data/opsdata_coal_node/coal_node/events/.index.db
opsdata_coal_node-0.1.5.data/data/opsdata_coal_node/coal_node/events/2019/01/19/2019-01-19T10-02-16-1584c.xml
opsdata_coal_node-0.1.5.data/data/opsdata_coal_node/coal_node/events/2019/01/19/2019-01-19T13-57-15-4e5aa.xml
opsdata_coal_node-0.1.5.data/data/opsdata_coal_node/coal_node/events/2019/01/21/2019-01-21T11-50-32-914c4.xml
opsdata_coal_node-0.1.5.data/data/opsdata_coal_node/coal_node/events/2019/01/24/2019-01-24T01-58-00-026af.xml
opsdata_coal_node-0.1.5.data/data/opsdata_coal_node/coal_node/events/2019/01/28/2019-01-28T20-54-47-e20c3.xml
opsdata_coal_node-0.1.5.data/data/opsdata_coal_node/coal_node/stations/inv.xml
opsdata_coal_node-0.1.5.data/data/opsdata_coal_node/coal_node/waveforms/.index.h5
opsdata_coal_node-0.1.5.data/data/opsdata_coal_node/coal_node/waveforms/2018-05-22T17-02-16.mseed
opsdata_coal_node-0.1.5.data/data/opsdata_coal_node/coal_node/waveforms/2018-05-22T20-57-15.mseed
opsdata_coal_node-0.1.5.dist-info/LICENSE
opsdata_coal_node-0.1.5.dist-info/METADATA
opsdata_coal_node-0.1.5.dist-info/WHEEL
opsdata_coal_node-0.1.5.dist-info/entry_points.txt
opsdata_coal_node-0.1.5.dist-info/top_level.txt
opsdata_coal_node-0.1.5.dist-info/RECORD
